gramform/__init__.py
gramform/dfops.py
gramform/grammar.py
gramform/imops.py
gramform/_resources/desc-confounds_timeseries.json
gramform/_resources/desc-confounds_timeseries.tsv
gramform/_results/.empty
gramform/_results/gm.nii.gz
gramform/_results/imops_logic.png
gramform/_results/imops_morphology.png
gramform/_results/wmcsf.nii.gz
gramform-0.0.0.dev0.dist-info/LICENSE
gramform-0.0.0.dev0.dist-info/METADATA
gramform-0.0.0.dev0.dist-info/WHEEL
gramform-0.0.0.dev0.dist-info/top_level.txt
gramform-0.0.0.dev0.dist-info/RECORD
