Metadata-Version: 2.1
Name: gramform
Version: 0.0.0.dev0
Summary: Grammar for string-to-function formulae
Author-email: Rastko Ciric <rastko@stanford.edu>
Maintainer-email: Rastko Ciric <rastko@stanford.edu>
License: Apache License
Project-URL: Homepage, https://github.com/hypercoil/gramform
Classifier: Programming Language :: Python :: 3
Classifier: License :: OSI Approved :: Apache Software License
Classifier: Operating System :: POSIX :: Linux
Classifier: Operating System :: MacOS :: MacOS X
Requires-Python: >=3.10
License-File: LICENSE
Provides-Extra: dfops
Requires-Dist: pandas ; extra == 'dfops'
Provides-Extra: full
Requires-Dist: pandas ; extra == 'full'
Requires-Dist: nibabel ; extra == 'full'
Requires-Dist: jax >=0.3.16 ; extra == 'full'
Provides-Extra: imops
Requires-Dist: nibabel ; extra == 'imops'
Requires-Dist: jax >=0.3.16 ; extra == 'imops'
Provides-Extra: test
Requires-Dist: matplotlib ; extra == 'test'
Requires-Dist: pytest ; extra == 'test'
Requires-Dist: pytest-cov ; extra == 'test'
Requires-Dist: coverage[toml] ; extra == 'test'
Requires-Dist: ruff ; extra == 'test'
Requires-Dist: blue ; extra == 'test'
Requires-Dist: templateflow ; extra == 'test'
